Workbook

Sheet Lisez-moi
A1: MODÈLE FINANCIER — 5 business à Antananarivo (2026)
A2: Compagnon du rapport RAPPORT.html · toutes les cellules jaunes sont modifiables
A4: MODE D'EMPLOI
A5: 1. Cellules jaunes = hypothèses à adapter à votre situation.
A6: 2. Cellules grises = calculs automatiques (ne pas saisir).
A7: 3. Chaque onglet est indépendant : modifiez volumes, prix et charges, tout se recalcule.
A8: 4. Montants mensuels, hors impôts (impôt synthétique 5 % ou IR 20 %).
A9: 5. Les résultats sont des estimations de travail, pas des garanties.
A11: LES 5 MODÈLES
A12: A — Micro-agence numérique à l'export | B12: Capital 1,5 M Ar | C12: Facturation en euros, marge nette 50-65 % | E12: A-Numerique
A13: B — Achats groupés de quartier | B13: Capital 0-1 M Ar | C13: Précommande + mobile money, marge 6-10 % du GMV | E13: B-Achats
A14: C — Logistique urbaine B2B | B14: Capital 5-15 M Ar | C14: Coursier moto, abonnements entreprises | E14: C-Logistique
A15: D — Eau : abonnement et kiosque | B15: Capital 4,5-12 M Ar | C15: Bonbonnes 20 L, contrats bureaux | E15: D-Eau
A16: E — Froid & solaire | B16: Capital 3-5 M Ar | C16: Installation + maintenance, acompte client | E16: E-Solaire
A18: RAPPELS DE COÛTS 2026 (à vérifier avant usage)
A19: Taux de change de travail | B19: 1 € = 4 800 Ar
A20: SMIG | B20: 300 000 Ar/mois
A21: Charges patronales CNaPS | B21: ≈ 13 %
A22: Carburant SP95 / gasoil | B22: 5 300 / 4 860 Ar par litre
A23: Impôt synthétique / IR | B23: 5 % du CA / 20 % du bénéfice
A24: TVA | B24: 20 % (seuil à confirmer auprès de la DGI)
A25: Microfinance | B25: 1,3 à 2,5 % par mois
A26: Taux directeur BFM | B26: 12 %

Sheet Paramètres
A1: Paramètres généraux
A2: Ces valeurs alimentent les autres onglets
A4: HYPOTHÈSES COMMUNES
A5: Taux de change (Ar pour 1 €) | B5: 4800 | C5: à réactualiser chaque mois
A6: Jours d'activité par mois | B6: 26
A7: Charges sociales patronales (CNaPS) | B7: 0.13
A8: Impôt synthétique (information) | B8: 0.05 | C8: non déduit dans les calculs

Sheet A-Numerique
A1: PLAN A — Micro-agence numérique à l'export
A2: Vendre en euros une compétence produite à coût local
A4: HYPOTHÈSES (à modifier)
A5: Clients en abonnement | B5: 2 | C5: objectif à 6 mois
A6: Prix moyen de l'abonnement (€/mois/client) | B6: 750 | C6: marché : 700-1 200 €
A7: Projets ponctuels par mois | B7: 1
A8: Prix moyen d'un projet (€) | B8: 400 | C8: moyenne lissée
A9: Salaire du fondateur (Ar) | B9: 1200000
A10: Salaire d'un développeur (Ar) | B10: 900000 | C10: profil confirmé
A11: Nombre de développeurs | B11: 1
A12: Charges sociales | B12: 0.13
A13: Internet + sauvegarde électrique (Ar) | B13: 400000 | C13: onduleur / solaire
A14: Outils logiciels (Ar) | B14: 250000 | C14: GitHub, Figma, hébergement, IA
A15: Prospection et marketing (Ar) | B15: 300000
A16: Comptabilité, banque, divers (Ar) | B16: 200000
A17: Investissement initial (Ar) | B17: 1500000 | C17: hors ordinateurs déjà possédés
A19: RÉSULTATS (calculés)
A20: Chiffre d'affaires mensuel (€) | B20: =B5*B6+B7*B8
A21: Chiffre d'affaires mensuel (Ar) | B21: =B20*Paramètres!$B$5
A22: Charges salariales | B22: =(B9+B10*B11)*(1+B12)
A23: Autres charges | B23: =B13+B14+B15+B16
A24: Total des charges | B24: =B22+B23
A25: RÉSULTAT NET MENSUEL | B25: =B21-B24
A26: Marge nette | B26: =IF(B21=0,0,B25/B21)
A27: Seuil de rentabilité (€ / mois) | B27: =B24/Paramètres!$B$5
A28: Retour sur investissement | B28: =IF(B25>0,B17/B25,"non rentable")
A29: Chiffre d'affaires annualisé | B29: =B21*12
A30: Résultat net annualisé | B30: =B25*12
A32: SENSIBILITÉ — nombre de clients en abonnement
A33: Clients | B33: CA mensuel (€) | C33: CA mensuel (Ar) | D33: Charges (Ar) | E33: Résultat net (Ar) | F33: Marge
A34: 1 | B34: =A34*B6+B7*B8 | C34: =B34*Paramètres!$B$5 | D34: =B24 | E34: =C34-D34 | F34: =IF(C34=0,0,E34/C34)
A35: 2 | B35: =A35*B6+B7*B8 | C35: =B35*Paramètres!$B$5 | D35: =B24 | E35: =C35-D35 | F35: =IF(C35=0,0,E35/C35)
A36: 3 | B36: =A36*B6+B7*B8 | C36: =B36*Paramètres!$B$5 | D36: =B24 | E36: =C36-D36 | F36: =IF(C36=0,0,E36/C36)
A37: 4 | B37: =A37*B6+B7*B8 | C37: =B37*Paramètres!$B$5 | D37: =B24 | E37: =C37-D37 | F37: =IF(C37=0,0,E37/C37)
A38: 5 | B38: =A38*B6+B7*B8 | C38: =B38*Paramètres!$B$5 | D38: =B24 | E38: =C38-D38 | F38: =IF(C38=0,0,E38/C38)

Sheet B-Achats
A1: PLAN B — Achats groupés de quartier
A2: Précommande payée → achat groupé → livraison hebdomadaire
A4: HYPOTHÈSES (à modifier)
A5: Panier moyen par commande (Ar) | B5: 90000 | C5: riz 25 kg + huile + sucre
A6: Clients actifs | B6: 250
A7: Commandes par client et par mois | B7: 1.5
A8: Marge brute moyenne | B8: 0.08 | C8: riz 5-7 %, gaz 10-12 %
A9: Assistant (Ar) | B9: 400000
A10: Transport et manutention (Ar) | B10: 250000 | C10: camion loué à la journée
A11: Emballage et impression (Ar) | B11: 80000
A12: Marketing et parrainage (Ar) | B12: 150000
A13: Téléphone, data, frais mobile money (Ar) | B13: 60000
A14: Investissement initial (Ar) | B14: 500000 | C14: sacs, balance, enseigne
A16: RÉSULTATS
A17: Volume d'affaires mensuel (GMV) | B17: =B5*B6*B7
A18: Nombre de commandes par mois | B18: =B6*B7
A19: Marge brute | B19: =B17*B8
A20: Charges fixes | B20: =B9+B10+B11+B12+B13
A21: RÉSULTAT NET MENSUEL | B21: =B19-B20
A22: Marge nette (en % du GMV) | B22: =IF(B17=0,0,B21/B17)
A23: Seuil de rentabilité (GMV mensuel) | B23: =IF(B8=0,0,B20/B8)
A24: Soit un nombre de commandes | B24: =IF(B5=0,0,B23/B5)
A25: Retour sur investissement | B25: =IF(B21>0,B14/B21,"non rentable")
A27: SENSIBILITÉ — GMV mensuel
A28: GMV mensuel | B28: Marge brute | C28: Charges fixes | D28: Résultat net
A29: 10000000 | B29: =A29*B8 | C29: =B20 | D29: =B29-C29
A30: 20000000 | B30: =A30*B8 | C30: =B20 | D30: =B30-C30
A31: 33750000 | B31: =A31*B8 | C31: =B20 | D31: =B31-C31
A32: 60000000 | B32: =A32*B8 | C32: =B20 | D32: =B32-C32
A33: 100000000 | B33: =A33*B8 | C33: =B20 | D33: =B33-C33

Sheet C-Logistique
A1: PLAN C — Logistique urbaine B2B
A2: Coursier moto, abonnements restaurants et e-commerçants
A4: HYPOTHÈSES (à modifier)
A5: Nombre de motos | B5: 3 | C5: démarrer avec 1 si le carnet est vide
A6: Courses par moto et par jour | B6: 20 | C6: maximum réaliste en circulation dense
A7: Tarif moyen par course (Ar) | B7: 5000 | C7: 4 000-7 000 Ar intra-Tana
A8: Jours d'activité par mois | B8: 26
A9: Commission du livreur (% du CA, carburant inclus) | B9: 0.4 | C9: standard du marché
A10: Entretien par moto et par mois (Ar) | B10: 70000
A11: Assurance par moto et par mois (Ar) | B11: 25000
A12: Superviseur / dispatch (Ar) | B12: 600000 | C12: 0 si vous dispatchez vous-même
A13: Local et parking (Ar) | B13: 250000
A14: Marketing (Ar) | B14: 200000
A15: Administration (Ar) | B15: 150000
A16: Prix d'une moto (Ar) | B16: 4250000
A17: Équipement par moto (Ar) | B17: 250000 | C17: casque, caisse, immatriculation
A18: Fonds de roulement (Ar) | B18: 1000000
A20: RÉSULTATS
A21: Chiffre d'affaires mensuel | B21: =B5*B6*B7*B8
A22: Commissions des livreurs | B22: =-B21*B9
A23: Entretien + assurance | B23: =-B5*(B10+B11)
A24: Marge sur coûts variables | B24: =B21+B22+B23
A25: Charges fixes | B25: =B12+B13+B14+B15
A26: RÉSULTAT NET MENSUEL | B26: =B24-B25
A27: Marge nette | B27: =IF(B21=0,0,B26/B21)
A28: Investissement total | B28: =B5*(B16+B17)+B18
A29: Retour sur investissement | B29: =IF(B26>0,B28/B26,"non rentable")
A31: SENSIBILITÉ — nombre de motos (superviseur activé à partir de 2 motos)
A32: Motos | B32: CA mensuel | C32: Marge variable | D32: Charges fixes | E32: Résultat net
A33: 1 | B33: =A33*B6*B7*B8 | C33: =B33*(1-B9)-A33*(B10+B11) | D33: =B13+B14+B15+IF(A33>1,B12,0) | E33: =C33-D33
A34: 2 | B34: =A34*B6*B7*B8 | C34: =B34*(1-B9)-A34*(B10+B11) | D34: =B13+B14+B15+IF(A34>1,B12,0) | E34: =C34-D34
A35: 3 | B35: =A35*B6*B7*B8 | C35: =B35*(1-B9)-A35*(B10+B11) | D35: =B13+B14+B15+IF(A35>1,B12,0) | E35: =C35-D35
A36: 4 | B36: =A36*B6*B7*B8 | C36: =B36*(1-B9)-A36*(B10+B11) | D36: =B13+B14+B15+IF(A36>1,B12,0) | E36: =C36-D36
A37: 6 | B37: =A37*B6*B7*B8 | C37: =B37*(1-B9)-A37*(B10+B11) | D37: =B13+B14+B15+IF(A37>1,B12,0) | E37: =C37-D37

Sheet D-Eau
A1: PLAN D — Eau : abonnement et kiosque
A2: Bonbonnes de 20 L, contrats bureaux, livraison à domicile
A4: HYPOTHÈSES (à modifier)
A5: Bonbonnes livrées par jour | B5: 45
A6: Prix d'une bonbonne livrée (Ar) | B6: 2500 | C6: sous le prix de crise (3 000 Ar)
A7: Bonbonnes vendues au kiosque par jour | B7: 15
A8: Prix au kiosque (Ar) | B8: 1500
A9: Jours d'activité par mois | B9: 26
A10: Coût variable par bonbonne (Ar) | B10: 350 | C10: eau, filtres, UV, amortissement
A11: Employé de production et livraison (Ar) | B11: 450000
A12: Loyer du local (Ar) | B12: 350000 | C12: 20 à 30 m²
A13: Électricité et sauvegarde (Ar) | B13: 150000
A14: Transport (moto cargo / tricycle) (Ar) | B14: 300000
A15: Marketing et enseigne (Ar) | B15: 200000
A16: Investissement initial (Ar) | B16: 11500000 | C16: filtration, cuves, 120 bonbonnes, véhicule
A18: RÉSULTATS
A19: Chiffre d'affaires mensuel | B19: =(B5*B6+B7*B8)*B9
A20: Bonbonnes vendues par mois | B20: =(B5+B7)*B9
A21: Coûts variables | B21: =B20*B10
A22: Marge sur coûts variables | B22: =B19-B21
A23: Charges fixes | B23: =B11+B12+B13+B14+B15
A24: RÉSULTAT NET MENSUEL | B24: =B22-B23
A25: Marge nette | B25: =IF(B19=0,0,B24/B19)
A26: Contribution moyenne par bonbonne | B26: =IF(B20=0,0,B22/B20)
A27: Seuil de rentabilité (bonbonnes par jour) | B27: =IF(B26=0,0,B23/(B26*B9))
A28: Retour sur investissement | B28: =IF(B24>0,B16/B24,"non rentable")
A30: SENSIBILITÉ — volume quotidien (répartition 75 % livré / 25 % kiosque)
A31: Bonbonnes / jour | B31: CA mensuel | C31: Coûts variables | D31: Charges fixes | E31: Résultat net
A32: 20 | B32: =A32*(0.75*B6+0.25*B8)*B9 | C32: =A32*B9*B10 | D32: =B23 | E32: =B32-C32-D32
A33: 40 | B33: =A33*(0.75*B6+0.25*B8)*B9 | C33: =A33*B9*B10 | D33: =B23 | E33: =B33-C33-D33
A34: 60 | B34: =A34*(0.75*B6+0.25*B8)*B9 | C34: =A34*B9*B10 | D34: =B23 | E34: =B34-C34-D34
A35: 80 | B35: =A35*(0.75*B6+0.25*B8)*B9 | C35: =A35*B9*B10 | D35: =B23 | E35: =B35-C35-D35
A36: 100 | B36: =A36*(0.75*B6+0.25*B8)*B9 | C36: =A36*B9*B10 | D36: =B23 | E36: =B36-C36-D36

Sheet E-Solaire
A1: PLAN E — Froid & solaire
A2: Installation, garantie et contrat de maintenance
A4: HYPOTHÈSES (à modifier)
A5: Installations par mois | B5: 2 | C5: démarrer à 1
A6: Prix moyen d'une installation (Ar) | B6: 14000000 | C6: 3 kW + batterie + congélateur
A7: Coût du matériel (% du prix) | B7: 0.68 | C7: panneaux, onduleur, batterie
A8: Main-d'œuvre par installation (Ar) | B8: 400000
A9: Nombre de techniciens | B9: 2
A10: Salaire d'un technicien (Ar) | B10: 900000 | C10: profil rare et cher
A11: Charges sociales | B11: 0.13
A12: Local / showroom (Ar) | B12: 700000
A13: Marketing (Ar) | B13: 500000
A14: Administration (Ar) | B14: 300000
A15: Investissement initial (Ar) | B15: 5000000 | C15: outillage + kit de démonstration
A17: RÉSULTATS
A18: Chiffre d'affaires mensuel | B18: =B5*B6
A19: Coût du matériel | B19: =B18*B7
A20: Main-d'œuvre d'installation | B20: =B5*B8
A21: Marge brute | B21: =B18-B19-B20
A22: Charges fixes | B22: =B9*B10*(1+B11)+B12+B13+B14
A23: RÉSULTAT NET MENSUEL | B23: =B21-B22
A24: Marge nette | B24: =IF(B18=0,0,B23/B18)
A25: Contribution par installation | B25: =B6*(1-B7)-B8
A26: Seuil de rentabilité (installations / mois) | B26: =IF(B25=0,0,B22/B25)
A27: Retour sur investissement | B27: =IF(B23>0,B15/B23,"non rentable")
A29: SENSIBILITÉ — nombre d'installations par mois
A30: Installations | B30: CA mensuel | C30: Marge brute | D30: Charges fixes | E30: Résultat net
A31: 1 | B31: =A31*B6 | C31: =B31*(1-B7)-A31*B8 | D31: =B22 | E31: =C31-D31
A32: 2 | B32: =A32*B6 | C32: =B32*(1-B7)-A32*B8 | D32: =B22 | E32: =C32-D32
A33: 3 | B33: =A33*B6 | C33: =B33*(1-B7)-A33*B8 | D33: =B22 | E33: =C33-D33
A34: 4 | B34: =A34*B6 | C34: =B34*(1-B7)-A34*B8 | D34: =B22 | E34: =C34-D34
A35: 6 | B35: =A35*B6 | C35: =B35*(1-B7)-A35*B8 | D35: =B22 | E35: =C35-D35

Sheet Comparaison
A1: COMPARAISON DES 5 MODÈLES
A2: Synthèse automatique — les valeurs se mettent à jour avec chaque onglet
A4: TABLEAU DE BORD
A5: Modèle | B5: Capital (Ar) | C5: Résultat net / mois | D5: Marge nette | E5: Retour (mois) | F5: Commentaire
A6: A — Micro-agence numérique | B6: ='A-Numerique'!B17 | C6: ='A-Numerique'!B25 | D6: ='A-Numerique'!B26 | E6: ='A-Numerique'!B28 | F6: Le meilleur ratio rendement / capital
A7: B — Achats groupés | B7: ='B-Achats'!B14 | C7: ='B-Achats'!B21 | D7: ='B-Achats'!B22 | E7: ='B-Achats'!B25 | F7: Faible marge, fort volume, zéro stock
A8: C — Logistique urbaine | B8: ='C-Logistique'!B28 | C8: ='C-Logistique'!B26 | D8: ='C-Logistique'!B27 | E8: ='C-Logistique'!B29 | F8: Rentable à partir de 2-3 motos
A9: D — Eau | B9: ='D-Eau'!B16 | C9: ='D-Eau'!B24 | D9: ='D-Eau'!B25 | E9: ='D-Eau'!B28 | F9: Business de densité : 30 bonbonnes/jour minimum
A10: E — Froid & solaire | B10: ='E-Solaire'!B15 | C10: ='E-Solaire'!B23 | D10: ='E-Solaire'!B24 | E10: ='E-Solaire'!B27 | F10: Compétence technique = barrière à l'entrée
A12: LECTURE
A13: 1. La micro-agence et le solaire offrent les meilleurs retours, mais exigent une compétence rare.
A14: 2. L'eau et la logistique sont des business de volume : la rentabilité dépend du taux d'utilisation.
A15: 3. Les achats groupés ont la marge la plus faible : ils ne fonctionnent que par le volume et la confiance.
A16: 4. Aucun de ces modèles ne devient rentable sans un minimum de clients récurrents.
A17: 5. Vérifiez chaque hypothèse sur le terrain avant d'engager du capital.
